./.gitignore
./.python-version
./CONTRIBUTING.md
./LICENSE
./MANIFEST.in
./PKG-INFO
./README.md
./SECURITY.md
./main.py
./pyproject.toml
./pytest.ini
./test_main.py
./uv.lock
./.github/pull_request_template.md
./.github/ISSUE_TEMPLATE/bug_report.md
./.github/ISSUE_TEMPLATE/feature_request.md
./.github/workflows/release.yml
./.github/workflows/test.yml
./docs/TESTING.md
./examples/claude-desktop-config.json
istat_mcp_server-0.1.2.dist-info/METADATA
istat_mcp_server-0.1.2.dist-info/WHEEL
istat_mcp_server-0.1.2.dist-info/entry_points.txt
istat_mcp_server-0.1.2.dist-info/licenses/LICENSE
istat_mcp_server-0.1.2.dist-info/RECORD
