Metadata-Version: 2.4
Name: istat-mcp-server
Version: 0.1.2
Summary: Model Context Protocol server for accessing Italian National Statistical Institute (ISTAT) data
Project-URL: Homepage, https://github.com/Halpph/istat-mcp-server
Project-URL: Documentation, https://github.com/Halpph/istat-mcp-server#readme
Project-URL: Repository, https://github.com/Halpph/istat-mcp-server
Project-URL: Issues, https://github.com/Halpph/istat-mcp-server/issues
Author-email: Alessio Cesaretti <alessio.cesaretti@hotmail.it>
License: MIT
License-File: LICENSE
Keywords: claude,data,istat,italy,llm,mcp,sdmx,statistics
Classifier: Development Status :: 4 - Beta
Classifier: Intended Audience :: Developers
Classifier: Intended Audience :: Science/Research
Classifier: License :: OSI Approved :: MIT License
Classifier: Programming Language :: Python :: 3
Classifier: Programming Language :: Python :: 3.10
Classifier: Programming Language :: Python :: 3.11
Classifier: Programming Language :: Python :: 3.12
Classifier: Topic :: Scientific/Engineering :: Information Analysis
Classifier: Topic :: Software Development :: Libraries :: Python Modules
Requires-Python: >=3.10
Requires-Dist: istatapi>=1.0.0
Requires-Dist: mcp[cli,server]>=1.17.0
Requires-Dist: requests>=2.32.0
Provides-Extra: dev
Requires-Dist: hatchling>=1.18.0; extra == 'dev'
Requires-Dist: pytest-cov>=4.1.0; extra == 'dev'
Requires-Dist: pytest-mock>=3.12.0; extra == 'dev'
Requires-Dist: pytest>=8.0.0; extra == 'dev'
